multiwatch/__init__.py
multiwatch/monitor.py
multiwatch/read_file.py
multiwatch/runner.py
multiwatch/termination.py
multiwatch-1.0.7.dist-info/DESCRIPTION.rst
multiwatch-1.0.7.dist-info/METADATA
multiwatch-1.0.7.dist-info/RECORD
multiwatch-1.0.7.dist-info/WHEEL
multiwatch-1.0.7.dist-info/metadata.json
multiwatch-1.0.7.dist-info/top_level.txt
