Metadata-Version: 2.0
Name: multiwatch
Version: 1.0.7
Summary: A watcher for multiprocessing queues and processes, with a bunch of handy methods to deal with parallel execution.
Home-page: https://go.pelicandd.com/n/multiwatch
Author: Arseni Mourzenko
Author-email: arseni.mourzenko@pelicandd.com
License: MIT
Keywords: multiprocessing,parallel,process,queue
Platform: UNKNOWN
Requires-Dist: psutil (==5.7.0)
